gfe_client/__init__.py
gfe_client/api_client.py
gfe_client/configuration.py
gfe_client/rest.py
gfe_client/api/__init__.py
gfe_client/api/annotate_api.py
gfe_client/api/type_align_api.py
gfe_client/api/type_seq_api.py
gfe_client/models/__init__.py
gfe_client/models/error.py
gfe_client/models/feature.py
gfe_client/models/seqdiff.py
gfe_client/models/typing.py
gfe_client-0.0.4.data/scripts/gfecli
tests/__init__.py
tests/test_annotate_api.py
tests/test_error.py
tests/test_feature.py
tests/test_seqdiff.py
tests/test_type_align_api.py
tests/test_type_seq_api.py
tests/test_typing.py
gfe_client-0.0.4.dist-info/AUTHORS.rst
gfe_client-0.0.4.dist-info/COPYING
gfe_client-0.0.4.dist-info/COPYING.LESSER
gfe_client-0.0.4.dist-info/LICENSE
gfe_client-0.0.4.dist-info/METADATA
gfe_client-0.0.4.dist-info/WHEEL
gfe_client-0.0.4.dist-info/top_level.txt
gfe_client-0.0.4.dist-info/RECORD
